twint_wp/__init__.py
twint_wp/__version__.py
twint_wp/cli.py
twint_wp/config.py
twint_wp/datelock.py
twint_wp/feed.py
twint_wp/format.py
twint_wp/get.py
twint_wp/output.py
twint_wp/run.py
twint_wp/storage/__init__.py
twint_wp/storage/db.py
twint_wp/storage/elasticsearch.py
twint_wp/storage/write.py
twint_wp/storage/write_meta.py
twint_wp/token.py
twint_wp/tweet.py
twint_wp/url.py
twint_wp/user.py
twint_wp/verbose.py
twint_wp-0.1.3.dist-info/LICENSE
twint_wp-0.1.3.dist-info/WHEEL
twint_wp-0.1.3.dist-info/METADATA
twint_wp-0.1.3.dist-info/RECORD
