Metadata-Version: 2.1
Name: twint-wp
Version: 0.1.3
Summary: 
Author: coso
Author-email: cosocosa627@gmail.com
Requires-Python: >=3.6,<4.0
Classifier: Programming Language :: Python :: 3
Classifier: Programming Language :: Python :: 3.10
Classifier: Programming Language :: Python :: 3.6
Classifier: Programming Language :: Python :: 3.7
Classifier: Programming Language :: Python :: 3.8
Classifier: Programming Language :: Python :: 3.9
Requires-Dist: PySocks (>=1.7.1,<2.0.0)
Requires-Dist: aiodns (>=3.0.0,<4.0.0)
Requires-Dist: aiohttp (>=3.7.0,<4.0.0)
Requires-Dist: aiohttp-socks (<=0.4.1)
Requires-Dist: beautifulsoup4 (>=4.10.0,<5.0.0)
Requires-Dist: cchardet (>=2.1.7,<3.0.0)
Requires-Dist: elasticsearch (>=7.16.2,<8.0.0)
Requires-Dist: fake-useragent (>=0.1.11,<0.2.0)
Requires-Dist: geopy (>=2.2.0,<3.0.0)
Requires-Dist: googletransx (>=2.4.2,<3.0.0)
Requires-Dist: schedule (>=1.1.0,<2.0.0)
